sifreader
