Metadata-Version: 1.1
Name: sifreader
Version: 0.2.3
Summary: A library to read Andor SIF file
Home-page: https://github.com/lightingghost/sifreader
Author: Zhenpeng Zhou and Daniel R. Stephan
Author-email: zhenp3ngzhou@gmail.com
License: UNKNOWN
Download-URL: https://github.com/lightingghost/sifreader/archive/0.2.3.tar.gz
Keywords: SIF,Andor,Image,reader
Platform: UNKNOWN
Classifier: Development Status :: 3 - Alpha
